pydiscomotif/RMSD_calculation.py
pydiscomotif/__init__.py
pydiscomotif/constants.py
pydiscomotif/data_containers.py
pydiscomotif/index_folders_and_files.py
pydiscomotif/indexing.py
pydiscomotif/motif_search.py
pydiscomotif/motif_search_with_ShareableList.py
pydiscomotif/pydiscomotif.py
pydiscomotif/residue_data_dicts.py
pydiscomotif/utils.py
pydiscomotif-1.0.2.dist-info/entry_points.txt
pydiscomotif-1.0.2.dist-info/WHEEL
pydiscomotif-1.0.2.dist-info/METADATA
pydiscomotif-1.0.2.dist-info/RECORD
