Metadata-Version: 2.1
Name: pydiscomotif
Version: 1.0.2
Summary: Python tool for the discovery of similar 3D motifs across protein structures. 
Author-email: Gabriel Cia <gabriel-_cia@hotmail.com>
Requires-Python: >=3.9
Requires-Dist: numba
Requires-Dist: click
Requires-Dist: biopython <=1.79
Requires-Dist: networkx
Requires-Dist: scipy
Requires-Dist: pandas
Requires-Dist: numpy
Requires-Dist: typing_extensions
Requires-Dist: tqdm
Project-URL: Home, https://github.com
